ml_framework/__init__.py
ml_framework/base/__init__.py
ml_framework/base/base_component.py
ml_framework/base/workflow_manager.py
ml_framework/components/__init__.py
ml_framework/components/comparator.py
ml_framework/components/connector.py
ml_framework/components/distillator.py
ml_framework/components/evaluator.py
ml_framework/components/explainer.py
ml_framework/components/inferer.py
ml_framework/components/monitorer.py
ml_framework/components/pusher.py
ml_framework/components/sequencer.py
ml_framework/components/tuner.py
ml_framework-0.0.18.dist-info/METADATA
ml_framework-0.0.18.dist-info/WHEEL
ml_framework-0.0.18.dist-info/top_level.txt
ml_framework-0.0.18.dist-info/RECORD
