Metadata-Version: 2.1
Name: ml-framework
Version: 0.0.18
Summary: Machine Learning Framework
Home-page: https://github.com/antsticky/AILib/
Author: feketedavid1012&ansticky
Author-email: antsticky@gmail.com
License: MIT
Download-URL: https://github.com/antsticky/AILib/archive/refs/tags/0.0.3.tar.gz
Project-URL: Bug Tracker, https://github.com/antsticky/AILib//issues
Keywords: framework,ML,AI
Platform: UNKNOWN
Classifier: Development Status :: 3 - Alpha
Classifier: Intended Audience :: Developers
Classifier: Topic :: Software Development :: Documentation
Classifier: License :: OSI Approved :: MIT License
Classifier: Programming Language :: Python :: 3
Classifier: Programming Language :: Python :: 3.7
Classifier: Programming Language :: Python :: 3.8
Classifier: Programming Language :: Python :: 3.9
Requires-Dist: requests
